pyapns_client/__init__.py
pyapns_client/client.py
pyapns_client/exceptions.py
pyapns_client/logging.py
pyapns_client/notification.py
pyapns_client-2.0.6.dist-info/LICENSE.rst
pyapns_client-2.0.6.dist-info/METADATA
pyapns_client-2.0.6.dist-info/WHEEL
pyapns_client-2.0.6.dist-info/top_level.txt
pyapns_client-2.0.6.dist-info/RECORD
