Metadata-Version: 2.1
Name: pyapns-client
Version: 2.0.6
Summary: Simple, flexible and fast Apple Push Notifications on iOS, OSX and Safari using the HTTP/2 Push provider API.
Home-page: https://github.com/kukosk/pyapns_client
Author: Jakub Kleň
Author-email: kukosk@gmail.com
License: MIT License
Keywords: apns apple ios osx safari push notifications
Platform: any
Classifier: Development Status :: 5 - Production/Stable
Classifier: Intended Audience :: Developers
Classifier: Operating System :: OS Independent
Classifier: License :: OSI Approved :: MIT License
Classifier: Topic :: Communications
Classifier: Topic :: Internet
Classifier: Topic :: Software Development :: Libraries :: Python Modules
Classifier: Topic :: Utilities
Classifier: Programming Language :: Python
Classifier: Programming Language :: Python :: 3
Classifier: Programming Language :: Python :: 3.6
Classifier: Programming Language :: Python :: 3.7
Classifier: Programming Language :: Python :: 3.8
Classifier: Programming Language :: Python :: 3.9
Classifier: Programming Language :: Python :: 3.10
License-File: LICENSE.rst
Requires-Dist: httpx[http2]
Requires-Dist: PyJWT (>=2)
Requires-Dist: cryptography
Requires-Dist: pytz
